LICENSE
README.rst
pyproject.toml
i18naddress/__init__.py
i18naddress/downloader.py
i18naddress/scripts.py
i18naddress/data/ac.json
i18naddress/data/ad.json
i18naddress/data/ae.json
i18naddress/data/af.json
i18naddress/data/ag.json
i18naddress/data/ai.json
i18naddress/data/al.json
i18naddress/data/all.json
i18naddress/data/am.json
i18naddress/data/ao.json
i18naddress/data/aq.json
i18naddress/data/ar.json
i18naddress/data/as.json
i18naddress/data/at.json
i18naddress/data/au.json
i18naddress/data/aw.json
i18naddress/data/ax.json
i18naddress/data/az.json
i18naddress/data/ba.json
i18naddress/data/bb.json
i18naddress/data/bd.json
i18naddress/data/be.json
i18naddress/data/bf.json
i18naddress/data/bg.json
i18naddress/data/bh.json
i18naddress/data/bi.json
i18naddress/data/bj.json
i18naddress/data/bl.json
i18naddress/data/bm.json
i18naddress/data/bn.json
i18naddress/data/bo.json
i18naddress/data/bq.json
i18naddress/data/br.json
i18naddress/data/bs.json
i18naddress/data/bt.json
i18naddress/data/bv.json
i18naddress/data/bw.json
i18naddress/data/by.json
i18naddress/data/bz.json
i18naddress/data/ca.json
i18naddress/data/cc.json
i18naddress/data/cd.json
i18naddress/data/cf.json
i18naddress/data/cg.json
i18naddress/data/ch.json
i18naddress/data/ci.json
i18naddress/data/ck.json
i18naddress/data/cl.json
i18naddress/data/cm.json
i18naddress/data/cn.json
i18naddress/data/co.json
i18naddress/data/cr.json
i18naddress/data/cu.json
i18naddress/data/cv.json
i18naddress/data/cw.json
i18naddress/data/cx.json
i18naddress/data/cy.json
i18naddress/data/cz.json
i18naddress/data/de.json
i18naddress/data/dj.json
i18naddress/data/dk.json
i18naddress/data/dm.json
i18naddress/data/do.json
i18naddress/data/dz.json
i18naddress/data/ec.json
i18naddress/data/ee.json
i18naddress/data/eg.json
i18naddress/data/eh.json
i18naddress/data/er.json
i18naddress/data/es.json
i18naddress/data/et.json
i18naddress/data/fi.json
i18naddress/data/fj.json
i18naddress/data/fk.json
i18naddress/data/fm.json
google_i18n_address-3.0.0.dist-info/METADATA
google_i18n_address-3.0.0.dist-info/WHEEL
google_i18n_address-3.0.0.dist-info/entry_points.txt
google_i18n_address-3.0.0.dist-info/licenses/LICENSE
google_i18n_address-3.0.0.dist-info/RECORD
