Metadata-Version: 2.1
Name: google-i18n-address
Version: 3.0.0
Summary: Address validation helpers for Google's i18n address database
Project-URL: Homepage, https://github.com/mirumee/google-i18n-address
Project-URL: Repository, https://github.com/mirumee/google-i18n-address
Project-URL: Bug Tracker, https://github.com/mirumee/google-i18n-address/issues
Author-email: Mirumee Software <hello@mirumee.com>
License-Expression: BSD-3-Clause
License-File: LICENSE
Classifier: Development Status :: 5 - Production/Stable
Classifier: Environment :: Web Environment
Classifier: Operating System :: OS Independent
Classifier: Programming Language :: Python
Classifier: Programming Language :: Python :: 3.7
Classifier: Programming Language :: Python :: 3.8
Classifier: Programming Language :: Python :: 3.9
Classifier: Programming Language :: Python :: 3.10
Classifier: Programming Language :: Python :: 3.11
Classifier: Topic :: Software Development :: Internationalization
Classifier: Topic :: Software Development :: Libraries :: Python Modules
Requires-Dist: requests>=2.7.0
Provides-Extra: dev
Requires-Dist: black; extra == 'dev'
Requires-Dist: ruff; extra == 'dev'
Provides-Extra: test
Requires-Dist: pytest; extra == 'test'
Requires-Dist: pytest-cov; extra == 'test'
